arlie/__about__.py
arlie/__init__.py
arlie/envs/__init__.py
arlie/envs/base_reward.py
arlie/envs/base_score.py
arlie/envs/manage.py
arlie/envs/registration.py
arlie/models/__init__.py
arlie/models/human.py
arlie/models/random.py
arlie-1.0.1.dist-info/METADATA
arlie-1.0.1.dist-info/WHEEL
arlie-1.0.1.dist-info/top_level.txt
arlie-1.0.1.dist-info/RECORD
